yuyu_scanner/__init__.py
yuyu_scanner/collect_url.py
yuyu_scanner/email.py
yuyu_scanner/files.py
yuyu_scanner/host.py
yuyu_scanner/information.py
yuyu_scanner/reverse_ip.py
yuyu_scanner/scan_port.py
yuyu_scanner/subdomain.py
yuyu_scanner/whois.py
yuyu-0.4.4.dist-info/METADATA
yuyu-0.4.4.dist-info/WHEEL
yuyu-0.4.4.dist-info/top_level.txt
yuyu-0.4.4.dist-info/RECORD
