Metadata-Version: 2.1
Name: yuyu
Version: 0.4.4
Summary: A simple package to make your own Information Gathering Scanner
Home-page: UNKNOWN
Author: Akas Wisnu Aji / justakazh
License: UNKNOWN
Platform: UNKNOWN
Classifier: Programming Language :: Python :: 3
Classifier: License :: OSI Approved :: MIT License
Classifier: Operating System :: OS Independent
Requires-Dist: python-Wappalyzer
Requires-Dist: requests
